MANIFEST.in
README.rst
classifiers.txt
djcli.py
setup.py
djcli.egg-info/PKG-INFO
djcli.egg-info/SOURCES.txt
djcli.egg-info/dependency_links.txt
djcli.egg-info/entry_points.txt
djcli.egg-info/requires.txt
djcli.egg-info/top_level.txt